qdrant_loader_core/__init__.py
qdrant_loader_core/logging.py
qdrant_loader_core/logging_filters.py
qdrant_loader_core/logging_processors.py
qdrant_loader_core/llm/__init__.py
qdrant_loader_core/llm/errors.py
qdrant_loader_core/llm/factory.py
qdrant_loader_core/llm/ratelimit.py
qdrant_loader_core/llm/settings.py
qdrant_loader_core/llm/tokenization.py
qdrant_loader_core/llm/types.py
qdrant_loader_core/llm/providers/__init__.py
qdrant_loader_core/llm/providers/azure_openai.py
qdrant_loader_core/llm/providers/ollama.py
qdrant_loader_core/llm/providers/openai.py
qdrant_loader_core-0.7.6.dist-info/METADATA
qdrant_loader_core-0.7.6.dist-info/WHEEL
qdrant_loader_core-0.7.6.dist-info/top_level.txt
qdrant_loader_core-0.7.6.dist-info/RECORD
